wabash/__init__.py
wabash/_wabash.cpython-310-x86_64-linux-gnu.so
wabash/libavcodec.so.62
wabash/libavfilter.so.11
wabash/libavformat.so.62
wabash/libavutil.so.60
wabash/libfdk-aac.so.2
wabash/libswresample.so.6
wabash/libswscale.so.9
wabash/libx264.so.165
wabash/libx265.so.215
wabash/gui/__init__.py
wabash/gui/display.py
wabash/gui/main.py
wabash/gui/model.py
wabash/gui/rockchip.py
wabash/gui/components/__init__.py
wabash/gui/components/errordialog.py
wabash/gui/components/fileselector.py
wabash/gui/components/theme.py
wabash/gui/components/waitdialog.py
wabash/gui/model/coco_80_labels_list.txt
wabash/gui/model/download_model.sh
wabash/gui/panels/__init__.py
wabash/gui/panels/network/adapterpanel.py
wabash/gui/panels/network/networkpanel.py
wabash/gui/panels/network/protocols/__init__.py
wabash/gui/panels/network/protocols/client.py
wabash/gui/panels/network/protocols/enums.py
wabash/gui/panels/network/protocols/listen.py
wabash/gui/panels/network/protocols/server.py
wabash/gui/panels/stream/layout.py
wabash/gui/panels/stream/manager.py
wabash/gui/panels/stream/memoryplot.py
wabash/gui/panels/stream/streampanel.py
wabash/gui/py_utils/__init__.py
wabash/gui/py_utils/coco_utils.py
wabash/gui/py_utils/onnx_executor.py
wabash/gui/py_utils/pytorch_executor.py
wabash/gui/py_utils/rknn_executor.py
wabash/gui/resources/branch_closed.png
wabash/gui/resources/branch_closed_lo.png
wabash/gui/resources/branch_open.png
wabash/gui/resources/branch_open_hi.png
wabash/gui/resources/branch_open_lo.png
wabash/gui/resources/checked.png
wabash/gui/resources/checked_hi.png
wabash/gui/resources/checked_lo.png
wabash/gui/resources/darkstyle.qss
wabash/gui/resources/small_arrow_left.png
wabash/gui/resources/small_arrow_left_hi.png
wabash/gui/resources/small_arrow_left_lo.png
wabash/gui/resources/small_arrow_up.png
wabash/gui/resources/small_arrow_up_hi.png
wabash/gui/resources/small_arrow_up_lo.png
wabash/gui/resources/spinner.gif
wabash-0.0.2.dist-info/METADATA
wabash-0.0.2.dist-info/WHEEL
wabash-0.0.2.dist-info/entry_points.txt
wabash-0.0.2.dist-info/RECORD
wabash-0.0.2.dist-info/licenses/LICENSE
wabash-0.0.2.dist-info/sboms/auditwheel.cdx.json
