Metadata-Version: 2.2
Name: wabash
Version: 0.0.2
Summary: Example pybind11 extension for multi-threading and data transfer
Author: Stephen Rhodes
Requires-Python: >=3.8
Requires-Dist: numpy
Requires-Dist: PyQt6-Qt6
Requires-Dist: pyqt6
Requires-Dist: loguru
Requires-Dist: requests
Requires-Dist: psutil
Requires-Dist: pyqtgraph
Requires-Dist: torch==2.8.0
Requires-Dist: torchvision==0.23.0
Requires-Dist: openvino==2025.3.0
